django_adminlink/__init__.py
django_adminlink/admin.py
django_adminlink/models.py
django_adminlink/static/js/single_admin_action.js
django_adminlink-0.3.0.dist-info/LICENSE
django_adminlink-0.3.0.dist-info/METADATA
django_adminlink-0.3.0.dist-info/WHEEL
django_adminlink-0.3.0.dist-info/top_level.txt
django_adminlink-0.3.0.dist-info/RECORD
